README.md
setup.py
pulumi_commercetools/__init__.py
pulumi_commercetools/_inputs.py
pulumi_commercetools/_utilities.py
pulumi_commercetools/api_client.py
pulumi_commercetools/api_extension.py
pulumi_commercetools/associate_role.py
pulumi_commercetools/attribute_group.py
pulumi_commercetools/cart_discount.py
pulumi_commercetools/category.py
pulumi_commercetools/channel.py
pulumi_commercetools/custom_object.py
pulumi_commercetools/customer_group.py
pulumi_commercetools/discount_code.py
pulumi_commercetools/get_state.py
pulumi_commercetools/get_type.py
pulumi_commercetools/outputs.py
pulumi_commercetools/product_discount.py
pulumi_commercetools/product_selection.py
pulumi_commercetools/product_type.py
pulumi_commercetools/project_settings.py
pulumi_commercetools/provider.py
pulumi_commercetools/pulumi-plugin.json
pulumi_commercetools/py.typed
pulumi_commercetools/shipping_method.py
pulumi_commercetools/shipping_zone.py
pulumi_commercetools/shipping_zone_rate.py
pulumi_commercetools/state.py
pulumi_commercetools/state_transitions.py
pulumi_commercetools/store.py
pulumi_commercetools/subscription.py
pulumi_commercetools/tax_category.py
pulumi_commercetools/tax_category_rate.py
pulumi_commercetools/type.py
pulumi_commercetools.egg-info/PKG-INFO
pulumi_commercetools.egg-info/SOURCES.txt
pulumi_commercetools.egg-info/dependency_links.txt
pulumi_commercetools.egg-info/not-zip-safe
pulumi_commercetools.egg-info/requires.txt
pulumi_commercetools.egg-info/top_level.txt
pulumi_commercetools/config/__init__.py
pulumi_commercetools/config/vars.py