Metadata-Version: 2.1
Name: pulumi-commercetools
Version: 1.14.1
Summary: A Pulumi package for creating and managing commercetools cloud resources.
Home-page: https://pulumi.io
License: Apache-2.0
Project-URL: Repository, https://github.com/unplatform-io/pulumi-commercetools
Keywords: pulumi commercetools
Requires-Python: >=3.8
